sgplib/__init__.py
sgplib-0.0.3.dist-info/LICENSE
sgplib-0.0.3.dist-info/METADATA
sgplib-0.0.3.dist-info/WHEEL
sgplib-0.0.3.dist-info/top_level.txt
sgplib-0.0.3.dist-info/RECORD
